{"cameraMode":{"drawMode":0,"name":"Shaded","section":"Shading Mode"},"sceneLighting":true,"audioPlay":false,"sceneViewState":{"m_AlwaysRefresh":false,"showFog":true,"showSkybox":true,"showFlares":true,"showImageEffects":true,"showParticleSystems":true,"showVisualEffectGraphs":true,"m_FxEnabled":true},"in2DMode":false,"pivot":{"x":117.48160552978516,"y":10.681106567382813,"z":-5.08925724029541},"rotation":{"x":-0.2986581325531006,"y":-0.014098076149821282,"z":0.004503797274082899,"w":-0.9542782306671143},"size":1.9875808954238892,"orthographic":false}